{
  "briefDescription": "    200g",
  "additionalDescription": "       !  10 ",
  "searchKeywords": ", , , , , , , , , , , , , , , 200g, , , , , , , , , , HACCP, , , , , , , , , , , , , , , 10, , , , , , , , ",
  "browserTitle": "[]200g -      |  ",
  "metaAuthor": " ",
  "metaDescription": "   !         .  10  []200g",
  "metaKeywords": ", , , , , , , , , , HACCP",
  "imageAltText": {
    "main": "[]200g   -     ",
    "detail1": "   -    ",
    "detail2": "   -    ",
    "detail3": "  -    "
  },
  "openGraph": {
    "title": "[]200g -  ",
    "description": "    !  10   ",
    "image": "https://ecimg.cafe24img.com/pg1966b42244249021/manwonyori/web/product/life/sutbul_yangnyeom_makchang/sutbul_yangnyeom_makchang_200g-1.jpg",
    "type": "product"
  },
  "productDetails": {
    "manufacturer": "",
    "brand": "",
    "weight": "200g",
    "storageMethod": "",
    "expirationDate": " 12",
    "mainIngredient": "(), "
  },
  "productTags": [
    "",
    "",
    "",
    "",
    "",
    "HACCP"
  ],
  "sellingPoints": [
    "  100%",
    "    ",
    "   ",
    " 10  ",
    "HACCP   "
  ]
}